qualibrate_app/__init__.py
qualibrate_app/__main__.py
qualibrate_app/api/__init__.py
qualibrate_app/api/__main__.py
qualibrate_app/api/core/__init__.py
qualibrate_app/api/core/domain/__init__.py
qualibrate_app/api/core/domain/bases/__init__.py
qualibrate_app/api/core/domain/bases/base_with_settings.py
qualibrate_app/api/core/domain/bases/branch.py
qualibrate_app/api/core/domain/bases/i_dump.py
qualibrate_app/api/core/domain/bases/load_type_flag.py
qualibrate_app/api/core/domain/bases/node.py
qualibrate_app/api/core/domain/bases/project.py
qualibrate_app/api/core/domain/bases/root.py
qualibrate_app/api/core/domain/bases/snapshot.py
qualibrate_app/api/core/domain/bases/storage.py
qualibrate_app/api/core/domain/local_storage/__init__.py
qualibrate_app/api/core/domain/local_storage/_id_to_local_path.py
qualibrate_app/api/core/domain/local_storage/branch.py
qualibrate_app/api/core/domain/local_storage/node.py
qualibrate_app/api/core/domain/local_storage/project.py
qualibrate_app/api/core/domain/local_storage/root.py
qualibrate_app/api/core/domain/local_storage/snapshot.py
qualibrate_app/api/core/domain/local_storage/utils/__init__.py
qualibrate_app/api/core/domain/local_storage/utils/filters.py
qualibrate_app/api/core/domain/local_storage/utils/node_utils.py
qualibrate_app/api/core/domain/local_storage/utils/snapshot_content.py
qualibrate_app/api/core/domain/timeline_db/__init__.py
qualibrate_app/api/core/domain/timeline_db/branch.py
qualibrate_app/api/core/domain/timeline_db/node.py
qualibrate_app/api/core/domain/timeline_db/project.py
qualibrate_app/api/core/domain/timeline_db/root.py
qualibrate_app/api/core/domain/timeline_db/snapshot.py
qualibrate_app/api/core/models/__init__.py
qualibrate_app/api/core/models/base.py
qualibrate_app/api/core/models/branch.py
qualibrate_app/api/core/models/node.py
qualibrate_app/api/core/models/paged.py
qualibrate_app/api/core/models/project.py
qualibrate_app/api/core/models/snapshot.py
qualibrate_app/api/core/models/storage.py
qualibrate_app-0.6.0.dist-info/METADATA
qualibrate_app-0.6.0.dist-info/WHEEL
qualibrate_app-0.6.0.dist-info/entry_points.txt
qualibrate_app-0.6.0.dist-info/RECORD
