Metadata-Version: 2.4
Name: qualibrate-app
Version: 0.6.0
Summary: 
Author: Quantum Machines
Author-email: info@quantum-machines.co
Requires-Python: >=3.10,<3.13
Classifier: Programming Language :: Python :: 3
Classifier: Programming Language :: Python :: 3.10
Classifier: Programming Language :: Python :: 3.11
Classifier: Programming Language :: Python :: 3.12
Provides-Extra: json-timeline-db
Requires-Dist: click (>=8.1.7,<8.2.0)
Requires-Dist: fastapi (>=0.117.1,<0.118.0)
Requires-Dist: jsonpatch (>=1.33,<2.0)
Requires-Dist: qualibrate-config (>=0.1.8,<0.2.0)
Requires-Dist: requests (>=2.32.4,<3.0.0)
Requires-Dist: tomli (>=2.0.1,<3.0.0) ; python_version < "3.11"
Requires-Dist: tomli-w (>=1.0.0,<2.0.0)
Requires-Dist: uvicorn (>=0.37.0,<0.38.0)
Project-URL: Repository, https://github.com/qua-platform/qualibrate-app
